{
  "name": "简体中文",
  "translations": {
    "generic.delete": "删除",
    "generic.save": "保存",
    "generic.text_size": "文字大小",
    "generic.rounding": "圆角程度",
    "generic.opacity": "不透明度",
    "generic.border": "边框",
    "generic.scale": "缩放比例",
    "generic.precision": "精度",
    "generic.text": "文本",
    "generic.prefix": "前缀",
    "generic.suffix": "后缀",
    "menu.profiles": "配置文件",
    "menu.modules": "模块",
    "menu.options": "选项",
    "menu.editHUD": "编辑HUD界面",
    "menu.back": "返回",
    "menu.add_profile": "添加配置",
    "menu.search_modules": "搜索模块",
    "menu.client_settings": "客户端设置",
    "menu.client_settings_description": "全局客户端设置",
    "menu.keybind_selector_tip": "按下按键绑定此设置",
    "menu.hud.tip": "点击/按住拖拽移动模块",
    "menu.hud.current_grid_size": "网格尺寸",
    "menu.upgrade": "升级到高级版",
    "menu.upgrade_unlock_mods": "解锁更多模块",
    "hudmodule.minecraft_font.name": "使用原版字体",
    "textmodule.padding_x.name": "水平内边距",
    "textmodule.padding_y.name": "垂直内边距",
    "bindmodule.button_text.name": "按钮文字",
    "module.autosprint.name": "自动疾跑",
    "module.autosprint.desc": "行走时自动触发疾跑",
    "module.cpsdisplay.name": "CPS计数器",
    "module.cpsdisplay.desc": "显示每秒点击次数",
    "module.armorhud.name": "装备HUD",
    "module.armorhud.desc": "显示穿戴的护甲和手持物品",
    "module.armorhud.setting.horizontal.name": "横向排列",
    "module.armorhud.setting.hotbar_background.name": "显示快捷栏背景",
    "module.armorhud.setting.durability.name": "显示耐久度",
    "module.armorhud.setting.adaptive_durability_color.name": "自适应耐久颜色",
    "module.armorhud.setting.item_size.name": "物品尺寸",
    "module.chunkborders.name": "区块边界",
    "module.chunkborders.desc": "显示区块分界线",
    "module.fpscounter.name": "帧数显示",
    "module.fpscounter.desc": "显示当前帧率(FPS)",
    "module.fullbright.name": "夜视模式",
    "module.fullbright.desc": "让世界保持最大亮度",
    "module.fullbright.setting.gamma.name": "伽马值",
    "module.hitboxes.name": "碰撞箱",
    "module.hitboxes.desc": "显示实体碰撞箱",
    "module.pingdisplay.name": "延迟显示",
    "module.pingdisplay.desc": "显示服务器连接延迟",
    "module.quickdrop.name": "快速丢弃",
    "module.quickdrop.desc": "触屏模式下快速丢弃物品",
    "module.quickdrop.setting.javadrop": "按住丢弃（Java版）",
    "module.quickperspective.name": "快速视角",
    "module.quickperspective.desc": "为触屏设备添加快速切换视角功能",
    "module.speeddisplay.name": "速度计",
    "module.speeddisplay.desc": "显示移动速度",
    "module.zoom.name": "动态变焦",
    "module.zoom.desc": "启用镜头缩放功能",
    "module.zoom.setting.modifier.name": "变焦调节",
    "module.zoom.setting.modifier.dpi_adjust.name": "灵敏度调节",
    "module.commandshortcuts.name": "指令快捷",
    "module.commandshortcuts.desc": "添加/gms、/gmc等指令快捷方式",
    "module.commandhotkey.name": "指令热键",
    "module.commandhotkey.desc": "将指令绑定至屏幕按钮和键盘按键",
    "module.commandhotkey.setting.command": "指令内容",
    "module.environment.name": "环境修改",
    "module.environment.desc": "调整环境视觉效果与天气",
    "module.environment.setting.editing_time.name": "修改时间",
    "module.environment.setting.time.name": "时间设置",
    "module.environment.setting.edit_weather.name": "修改天气",
    "module.environment.setting.rain_amount.name": "降雨强度",
    "module.environment.setting.thunder_amount.name": "雷暴强度",
    "module.coordinatesdisplay.name": "坐标显示",
    "module.coordinatesdisplay.desc": "显示玩家坐标信息",
    "module.texthotkey.name": "聊天热键",
    "module.texthotkey.desc": "将预设文本绑定至屏幕按钮和键盘按键",
    "module.viewmodel.name": "手持模型",
    "module.viewmodel.desc": "自定义手持物品的显示效果",
    "module.viewmodel.translationx.name": "水平位移",
    "module.viewmodel.translationy.name": "垂直位移",
    "module.viewmodel.translationz.name": "纵深位移",
    "module.viewmodel.rotationx.name": "X轴旋转",
    "module.viewmodel.rotationy.name": "Y轴旋转",
    "module.viewmodel.rotationz.name": "Z轴旋转",
    "module.hurtcam.name": "受伤抖动",
    "module.hurtcam.desc": "禁用受伤时的镜头抖动",
    "module.serverdisplay.name": "服务器显示",
    "module.serverdisplay.desc": "显示当前服务器信息",
    "module.serverdisplay.setting.show_featured_name.name": "显示精选服务器",
    "module.serverdisplay.setting.show_numeric_ip.name": "显示数字IP(x.x.x.x)",
    "module.keystrokes.name": "按键显示",
    "module.keystrokes.desc": "显示移动按键状态",
    "module.keystrokes.setting.keystroke_size.name": "按键尺寸",
    "module.keystrokes.setting.show_space_bar.name": "显示空格键",
    "module.keystrokes.setting.space_bar_height.name": "空格键高度",
    "module.keystrokes.setting.unpressed_color.name": "未按颜色",
    "module.keystrokes.setting.pressed_color.name": "按下颜色",
    "module.keystrokes.setting.unpressed_text_color.name": "未按文字颜色",
    "module.keystrokes.setting.pressed_text_color.name": "按下文字颜色",
    "module.pausegame.name": "暂停游戏",
    "module.pausegame.desc": "像Java版一样在菜单界面暂停单人游戏",
    "module.pausegame.game_is_paused": "游戏已暂停",
    "module.cinematic_camera.name": "电影镜头",
    "module.cinematic_camera.desc": "启用Java版风格的平滑镜头移动",
    "module.crosshair.name": "准星设置",
    "module.crosshair.desc": "自定义准星显示效果",
    "module.crosshair.setting.red_when_entity_in_reach.name": "目标靠近时变红",
    "module.crosshair.setting.red_when_entity_in_reach.desc": "当敌人处于攻击范围内时准星变红",
    "module.reachdisplay.name": "攻击距离",
    "module.reachdisplay.desc": "显示攻击实体时的有效距离",
    "module.thirdpersonnametag.name": "第三人称名牌",
    "module.thirdpersonnametag.desc": "在第三人称视角显示玩家名牌（需重进游戏生效）",
    "module.audiosubtitles.name": "声音字幕",
    "module.audiosubtitles.desc": "显示播放中的音效名称和方向",
    "module.freelook.name": "自由视角",
    "module.freelook.desc": "允许在角色静止时自由观察周围环境（360°视角）",
    "module.freelook.setting.hold.name": "按住激活",
    "module.freelook.setting.change_perspective.name": "切换视角",
    "module.freelook.setting.anti_strafe.name": "防侧移",
    "module.waypoints.name": "路标",
    "module.waypoints.desc": "查看客户端设置的路标，您可以在任意位置设置标记。使用指令(.waypoint)管理路标",
    "module.waypoints.waypoint_already_exists": "该路标已存在",
    "module.render_options.name": "渲染选项",
    "module.render_options.desc": "更改渲染选项以提高性能，可能会提升FPS",
    "module.render_options.setting.disable_entities.name": "禁用实体渲染",
    "module.render_options.setting.disable_block_entities.name": "禁用方块实体渲染",
    "module.render_options.setting.disable_particles.name": "禁用粒子效果",
    "module.block_overlay.name": "方块遮罩",
    "module.block_overlay.desc": "改变原版方块遮罩的外观",
    "module.block_overlay.setting.outline.name": "轮廓",
    "module.block_overlay.setting.color.name": "颜色",
    "module.block_overlay.setting.color2.name": "颜色2",
    "module.block_overlay.setting.color_wave.name": "颜色波动",
    "module.block_overlay.setting.color_wave_speed.name": "颜色波动速度",
    "module.motion_blur.name": "运动模糊",
    "module.motion_blur.desc": "在屏幕上产生运动模糊效果，适合高FPS且解锁FPS/VSync关闭的情况",
    "module.motion_blur.setting.intensity.name": "模糊强度",
    "module.tnt_timer.name": "TNT计时器",
    "module.tnt_timer.desc": "显示TNT爆炸前的倒计时",
    "module.tnt_timer.setting.fg_color.name": "前景色",
    "module.tnt_timer.setting.bg_color.name": "背景色",
    "settings.keyBind": "按键绑定",
    "settings.actionBind": "操作绑定",
    "settings.generic.red": "红色",
    "settings.generic.green": "绿色",
    "settings.generic.blue": "蓝色",
    "settings.generic.background_color": "背景颜色",
    "settings.generic.text_color": "文字颜色",
    "settings.generic.border_color": "边框颜色",
    "setting.show_modules_everywhere.name": "在所有界面显示模块",
    "setting.search_descriptions.name": "搜索模块描述",
    "setting.hud_snap_to_grid.name": "模块对齐网格",
    "setting.disable_vsync.name": "解锁FPS限制",
    "command.internal_error_message": "运行命令时发生内部错误",
    "command.toggle.module_not_found": "未找到模块",
    "command.say.invalid_length": "消息长度无效（必须为1-255字符）"
  }
}
